hostray/__init__.py
hostray/__main__.py
hostray/pack.yaml
hostray/unit_test/__init__.py
hostray/unit_test/base.py
hostray/unit_test/util.py
hostray/unit_test/util_orm.py
hostray/unit_test/util_worker.py
hostray/unit_test/web.py
hostray/util/__init__.py
hostray/util/asynccontextmanager.py
hostray/util/callbacks.py
hostray/util/constants.py
hostray/util/dt.py
hostray/util/dynamic_class_enum.py
hostray/util/hierarchy_element.py
hostray/util/local.csv
hostray/util/localization.py
hostray/util/logger.py
hostray/util/utils.py
hostray/util/orm/__init__.py
hostray/util/orm/access_executor_pool.py
hostray/util/orm/entity.py
hostray/util/worker_pool/__init__.py
hostray/util/worker_pool/pool.py
hostray/util/worker_pool/worker.py
hostray/web/__init__.py
hostray/web/client.py
hostray/web/config_validator.py
hostray/web/constants.py
hostray/web/httplocal.csv
hostray/web/local.csv
hostray/web/pack.py
hostray/web/server.py
hostray/web/component/__init__.py
hostray/web/component/base.py
hostray/web/component/default_component.py
hostray/web/component/optional_component.py
hostray/web/controller/__init__.py
hostray/web/controller/base.py
hostray/web/controller/db_cusd_controller.py
hostray/web/controller/default_controller.py
hostray/web/controller/request_controller.py
hostray/web/controller/streaming_controller.py
hostray/web/controller/unittest_controller.py
hostray/web/controller/web_socket_controller.py
hostray-0.7.5.1.dist-info/LICENSE
hostray-0.7.5.1.dist-info/METADATA
hostray-0.7.5.1.dist-info/WHEEL
hostray-0.7.5.1.dist-info/top_level.txt
hostray-0.7.5.1.dist-info/RECORD
