Metadata-Version: 2.1
Name: hostray
Version: 0.7.5.1
Summary: configurable module framework and utilties based on Tornado Web Server
Home-page: https://github.com/hsky77/hostray
Author: hsky77
Author-email: howardlkung@gmail.com
License: MIT License
Platform: UNKNOWN
Classifier: Programming Language :: Python :: 3
Classifier: Programming Language :: Python :: 3.6
Classifier: Programming Language :: Python :: 3.7
Classifier: License :: OSI Approved :: MIT License
Classifier: Operating System :: OS Independent
Requires-Python: >=3.6
Requires-Dist: tornado (>=6.0.3)
Requires-Dist: PyYAML (>=5.1.1)
Requires-Dist: sqlalchemy (>=1.3.5)
Requires-Dist: coloredlogs (>=10.0)
Requires-Dist: PyMySQL (>=0.9.3)
Requires-Dist: aiohttp (>=3.6.2)
Requires-Dist: requests (>=2.20.0)
